{
  "levelId": "x1di",
  "levelName": "Fountain of Youth",
  "players": [
    {
      "id": "human-player",
      "type": 0
    },
    {
      "id": "ai-player",
      "type": 1,
      "iterationsPerAlternative": 80,
      "aiAlgorithm": 0
    }
  ],
  "estimatedDifficulty": 0.27,
  "visibleHandPlayerId": "human-player",
  "initialCardsPerPlayer": 5,
  "cardsPerDirection": 3,
  "board": {
    "vertices": [
      {
        "id": "vxi2a",
        "position": {
          "x": 0.07142857142857144,
          "y": 0.07142857142857144
        },
        "linkedVertices": [
          "vx843"
        ]
      },
      {
        "id": "vx843",
        "position": {
          "x": 0.35714285714285715,
          "y": 0.07142857142857144
        },
        "linkedVertices": [
          "vxnw0",
          "vx1yw"
        ]
      },
      {
        "id": "vxnw0",
        "position": {
          "x": 0.35714285714285715,
          "y": 0.35714285714285715
        },
        "linkedVertices": [
          "vx48g"
        ]
      },
      {
        "id": "vx48g",
        "position": {
          "x": 0.07142857142857144,
          "y": 0.35714285714285715
        },
        "linkedVertices": [
          "vxi2a"
        ]
      },
      {
        "id": "vxzzp",
        "position": {
          "x": 0.6428571428571429,
          "y": 0.9285714285714286
        },
        "linkedVertices": [
          "vxrc3",
          "vx1yw"
        ]
      },
      {
        "id": "vxrc3",
        "position": {
          "x": 0.6428571428571429,
          "y": 0.6428571428571429
        },
        "linkedVertices": [
          "vxe7x"
        ]
      },
      {
        "id": "vxe7x",
        "position": {
          "x": 0.9285714285714286,
          "y": 0.6428571428571429
        },
        "linkedVertices": [
          "vxzpw"
        ]
      },
      {
        "id": "vxzpw",
        "position": {
          "x": 0.9285714285714286,
          "y": 0.9285714285714286
        },
        "linkedVertices": [
          "vxzzp"
        ]
      },
      {
        "id": "vx1yw",
        "position": {
          "x": 0.5,
          "y": 0.5
        },
        "linkedVertices": [
          "vxe7x",
          "vx48g"
        ]
      }
    ]
  }
}