{
  "levelId": "x0p7",
  "levelName": "Sorcerer's Stone",
  "players": [
    {
      "id": "human-player",
      "type": 0
    },
    {
      "id": "ai-player",
      "type": 1,
      "iterationsPerAlternative": 200,
      "aiAlgorithm": 0
    }
  ],
  "estimatedDifficulty": 0.72,
  "visibleHandPlayerId": "human-player",
  "initialCardsPerPlayer": 6,
  "cardsPerDirection": 3,
  "board": {
    "vertices": [
      {
        "id": "v1",
        "position": {
          "x": 0.07142857142857144,
          "y": 0.35714285714285715
        },
        "linkedVertices": [
          "v2",
          "vxwz7"
        ]
      },
      {
        "id": "v2",
        "position": {
          "x": 0.07142857142857144,
          "y": 0.6428571428571429
        },
        "linkedVertices": [
          "v3",
          "v8"
        ]
      },
      {
        "id": "v3",
        "position": {
          "x": 0.35714285714285715,
          "y": 0.9285714285714286
        },
        "linkedVertices": []
      },
      {
        "id": "v4",
        "position": {
          "x": 0.6428571428571429,
          "y": 0.9285714285714286
        },
        "linkedVertices": [
          "v9",
          "v5"
        ]
      },
      {
        "id": "v5",
        "position": {
          "x": 0.9285714285714286,
          "y": 0.6428571428571429
        },
        "linkedVertices": [
          "vx871"
        ]
      },
      {
        "id": "v7",
        "position": {
          "x": 0.6428571428571429,
          "y": 0.5
        },
        "linkedVertices": [
          "v9",
          "v5"
        ]
      },
      {
        "id": "v8",
        "position": {
          "x": 0.35714285714285715,
          "y": 0.5
        },
        "linkedVertices": [
          "vxwz7"
        ]
      },
      {
        "id": "v9",
        "position": {
          "x": 0.5,
          "y": 0.35714285714285715
        },
        "linkedVertices": [
          "v8",
          "v3"
        ]
      },
      {
        "id": "vxwz7",
        "position": {
          "x": 0.5,
          "y": 0.07142857142857144
        },
        "linkedVertices": [
          "v7",
          "vx871"
        ]
      },
      {
        "id": "vx871",
        "position": {
          "x": 0.9285714285714286,
          "y": 0.35714285714285715
        },
        "linkedVertices": []
      }
    ]
  }
}